gradle.properties
hexdoc_hexgender/__gradle_version__.py
hexdoc_hexgender/__init__.py
hexdoc_hexgender/__version__.py
hexdoc_hexgender/_hooks.py
hexdoc_hexgender/py.typed
hexdoc_hexgender/_export/.gitignore
hexdoc_hexgender/_export/__init__.py
hexdoc_hexgender/_export/generated/__init__.py
hexdoc_hexgender/_export/generated/hexgender.hexdoc.json
hexdoc_hexgender/_export/generated/hexgender.patterns.hexdoc.json
hexdoc_hexgender/_export/generated/assets/hexcasting/lang/en_us.flatten.json5
hexdoc_hexgender/_export/generated/assets/hexcasting/patchouli_books/thehexbook/en_us/entries/patterns/bust_patterns.json
hexdoc_hexgender/_export/generated/assets/hexcasting/patchouli_books/thehexbook/en_us/entries/patterns/spells/gender_interop.json
hexdoc_hexgender/_export/generated/assets/hexgender/lang/en_us.json
hexdoc_hexgender/_templates/__init__.py
hexdoc_hexgender-1.0.4.1.0.dist-info/METADATA
hexdoc_hexgender-1.0.4.1.0.dist-info/WHEEL
hexdoc_hexgender-1.0.4.1.0.dist-info/entry_points.txt
hexdoc_hexgender-1.0.4.1.0.dist-info/licenses/LICENSE
hexdoc_hexgender-1.0.4.1.0.dist-info/RECORD
